onehalfpiece/__init__.py
onehalfpiece/main.py
onehalfpiece/test_onehalfpiece.py
onehalfpiece-0.0.2.dist-info/LICENSE
onehalfpiece-0.0.2.dist-info/METADATA
onehalfpiece-0.0.2.dist-info/WHEEL
onehalfpiece-0.0.2.dist-info/top_level.txt
onehalfpiece-0.0.2.dist-info/RECORD
