Metadata-Version: 2.1
Name: onehalfpiece
Version: 0.0.2
Summary: Learn python how to package
Home-page: https://github.com/ryanzhang/onehalfpiece
Author: ryanzhang
Author-email: ryanzhangcheng@gmail.com
License: MIT License
Platform: UNKNOWN
License-File: LICENSE
Requires-Dist: six (>=1.9.0)
Provides-Extra: dev
Requires-Dist: prospector (>=0.10.2) ; extra == 'dev'
Provides-Extra: docs
Requires-Dist: Sphinx (>=1.3.1) ; extra == 'docs'
Provides-Extra: test
Requires-Dist: coverage (>=3.7.1) ; extra == 'test'
Requires-Dist: coveralls (>=0.5) ; extra == 'test'
Requires-Dist: nose (>=1.3.7) ; extra == 'test'
Requires-Dist: python-coveralls (>=2.5.0) ; extra == 'test'
